arsein/Arsein.py
arsein/Clien.py
arsein/Copyright.py
arsein/Device.py
arsein/Encoder.py
arsein/Error.py
arsein/ErrorRubika.py
arsein/GetDataMethod.py
arsein/Getheader.py
arsein/GtM.py
arsein/PostData.py
arsein/TypeText.py
arsein/Zedcontent.py
arsein/__init__.py
Arsein-7.8.6.dist-info/LICENCE
Arsein-7.8.6.dist-info/METADATA
Arsein-7.8.6.dist-info/WHEEL
Arsein-7.8.6.dist-info/top_level.txt
Arsein-7.8.6.dist-info/RECORD
